luxdb/__init__.py
luxdb/client.py
luxdb/commands.py
luxdb/connection.py
luxdb/exceptions.py
luxdb/index.py
luxdb/knn_store.py
luxdb/server.py
luxdb/sync_client.py
luxdb-0.0.10.dist-info/LICENSE
luxdb-0.0.10.dist-info/METADATA
luxdb-0.0.10.dist-info/WHEEL
luxdb-0.0.10.dist-info/top_level.txt
luxdb-0.0.10.dist-info/RECORD
