Metadata-Version: 2.1
Name: luxdb
Version: 0.0.10
Summary: Store multidimensional vectors and quickly search nearest neighbors.
Home-page: https://gitlab.com/sacovo/luxdb
Author: Sandro Covo
Author-email: sandro@sandrocovo.ch
License: UNKNOWN
Project-URL: Bug Tracker, https://gitlab.com/sacovo/luxdb/-/issues
Keywords: 'machine learning,encodings,vectors'
Platform: UNKNOWN
Classifier: Development Status :: 3 - Alpha
Classifier: Topic :: Database :: Database Engines/Servers
Classifier: Intended Audience :: Developers
Classifier: Intended Audience :: Science/Research
Classifier: Programming Language :: Python :: 3
Classifier: License :: OSI Approved :: MIT License
Classifier: Operating System :: OS Independent
Requires-Python: >=3.7
License-File: LICENSE
Requires-Dist: numpy
Requires-Dist: cryptography
